odoo/addons/product_variant_attribute_tax/README.rst
odoo/addons/product_variant_attribute_tax/__init__.py
odoo/addons/product_variant_attribute_tax/__manifest__.py
odoo/addons/product_variant_attribute_tax/i18n/es.po
odoo/addons/product_variant_attribute_tax/i18n/es_AR.po
odoo/addons/product_variant_attribute_tax/i18n/es_PA.po
odoo/addons/product_variant_attribute_tax/i18n/it.po
odoo/addons/product_variant_attribute_tax/i18n/product_variant_attribute_tax.pot
odoo/addons/product_variant_attribute_tax/models/__init__.py
odoo/addons/product_variant_attribute_tax/models/product_attribute_value.py
odoo/addons/product_variant_attribute_tax/readme/CONFIGURE.rst
odoo/addons/product_variant_attribute_tax/readme/CONTRIBUTORS.rst
odoo/addons/product_variant_attribute_tax/readme/DESCRIPTION.rst
odoo/addons/product_variant_attribute_tax/static/description/icon.png
odoo/addons/product_variant_attribute_tax/static/description/index.html
odoo/addons/product_variant_attribute_tax/views/product_attribute_views.xml
odoo_addon_product_variant_attribute_tax-16.0.1.0.1.dist-info/METADATA
odoo_addon_product_variant_attribute_tax-16.0.1.0.1.dist-info/WHEEL
odoo_addon_product_variant_attribute_tax-16.0.1.0.1.dist-info/top_level.txt
odoo_addon_product_variant_attribute_tax-16.0.1.0.1.dist-info/RECORD
